flake8_builtins.py
flake8_builtins-3.0.0.dist-info/METADATA
flake8_builtins-3.0.0.dist-info/WHEEL
flake8_builtins-3.0.0.dist-info/entry_points.txt
flake8_builtins-3.0.0.dist-info/licenses/LICENSE
flake8_builtins-3.0.0.dist-info/RECORD
