Metadata-Version: 2.4
Name: flake8-builtins
Version: 3.0.0
Summary: Check for python builtins being used as variables or parameters
Project-URL: Homepage, https://github.com/gforcada/flake8-builtins
Project-URL: Bug Tracker, https://github.com/gforcada/flake8-builtins/issues
Project-URL: Changelog, https://github.com/gforcada/flake8-builtins/blob/main/CHANGES.rst
Author-email: Gil Forcada Codinachs <gil.gnome@gmail.com>
License-File: LICENSE
Keywords: flake8,pep8,python
Classifier: Development Status :: 5 - Production/Stable
Classifier: Environment :: Console
Classifier: Framework :: Flake8
Classifier: Intended Audience :: Developers
Classifier: License :: OSI Approved :: GNU General Public License v2 (GPLv2)
Classifier: Operating System :: OS Independent
Classifier: Programming Language :: Python
Classifier: Programming Language :: Python :: 3
Classifier: Programming Language :: Python :: 3 :: Only
Classifier: Programming Language :: Python :: 3.9
Classifier: Programming Language :: Python :: 3.10
Classifier: Programming Language :: Python :: 3.11
Classifier: Programming Language :: Python :: 3.12
Classifier: Programming Language :: Python :: 3.13
Classifier: Programming Language :: Python :: Implementation :: CPython
Classifier: Programming Language :: Python :: Implementation :: PyPy
Classifier: Topic :: Software Development
Classifier: Topic :: Software Development :: Quality Assurance
Requires-Python: >=3.9
Requires-Dist: flake8
Provides-Extra: test
Requires-Dist: pytest; extra == 'test'
